aws_ecs_task_render/__init__.py
aws_ecs_task_render/__main__.py
aws_ecs_task_render/profile_checker.py
aws_ecs_task_render-0.6.0.dist-info/LICENSE
aws_ecs_task_render-0.6.0.dist-info/METADATA
aws_ecs_task_render-0.6.0.dist-info/WHEEL
aws_ecs_task_render-0.6.0.dist-info/entry_points.txt
aws_ecs_task_render-0.6.0.dist-info/top_level.txt
aws_ecs_task_render-0.6.0.dist-info/RECORD
