Metadata-Version: 2.1
Name: aws-ecs-task-render
Version: 0.6.0
Summary: "A package to edit image uri on ecs task definition"
Author: Luca Pisciotta
Author-email: luca.pisciotta@lptech.io
License: MIT
Keywords: aws,ecs,fargate
Platform: UNKNOWN
Classifier: Programming Language :: Python :: 3
Classifier: Programming Language :: Python :: 3.10
Classifier: Development Status :: 4 - Beta
License-File: LICENSE
Requires-Dist: boto3
Requires-Dist: botocore
Requires-Dist: inquirer
